c104/__init__.py
c104/__init__.pyi
c104/_c104.cpython-39-aarch64-linux-gnu.so
c104/py.typed
c104-2.2.1.dist-info/METADATA
c104-2.2.1.dist-info/WHEEL
c104-2.2.1.dist-info/top_level.txt
c104-2.2.1.dist-info/RECORD
c104-2.2.1.dist-info/licenses/LICENSE
