Metadata-Version: 2.4
Name: c104
Version: 2.2.1
Summary: A Python module to simulate SCADA and RTU communication over protocol 60870-5-104 to research ICT behavior in power grids.
Author-email: "Martin Unkel, Fraunhofer FIT" <martin.unkel@fit.fraunhofer.de>
License:                     GNU GENERAL PUBLIC LICENSE
Project-URL: Documentation, https://iec104-python.readthedocs.io/latest/python/index.html
Project-URL: Bug Tracker, https://github.com/Fraunhofer-FIT-DIEN/iec104-python/issues
Project-URL: Changelog, https://iec104-python.readthedocs.io/latest/changelog.html
Project-URL: Source Code, https://github.com/Fraunhofer-FIT-DIEN/iec104-python
Keywords: Python bindings,scada,rtu,remote-terminal-unit,mtu,master-terminal-unit,energy-management,60870-5-104,iec60870-5-104,iec60870-5,60870,lib60870,lib60870-C
Classifier: Development Status :: 5 - Production/Stable
Classifier: Intended Audience :: Developers
Classifier: Intended Audience :: Education
Classifier: Intended Audience :: Information Technology
Classifier: Intended Audience :: Science/Research
Classifier: License :: OSI Approved :: GNU General Public License v3 (GPLv3)
Classifier: Programming Language :: C
Classifier: Programming Language :: C++
Classifier: Programming Language :: Python :: 3 :: Only
Classifier: Programming Language :: Python :: 3.7
Classifier: Programming Language :: Python :: 3.8
Classifier: Programming Language :: Python :: 3.9
Classifier: Programming Language :: Python :: 3.10
Classifier: Programming Language :: Python :: 3.11
Classifier: Programming Language :: Python :: 3.12
Classifier: Programming Language :: Python :: 3.13
Classifier: Topic :: Scientific/Engineering :: Interface Engine/Protocol Translator
Classifier: Topic :: Software Development :: Libraries :: Python Modules
Classifier: Topic :: System :: Emulators
Classifier: Topic :: System :: Networking :: Monitoring
Classifier: Topic :: Utilities
Classifier: Typing :: Typed
Requires-Python: >=3.7
License-File: LICENSE
Dynamic: license-file
